Metadata-Version: 2.1
Name: SajadXS
Version: 1.5
Summary: Composable HTTP middleware for requests
Author: SajadXS
Classifier: Programming Language :: Python :: 3
